{
  "scenes": [
    "game.json"
  ],
  "resources": [
    {"path": "ship1.png", "frames": 2, "speed": 0.5},
    {"path": "ship2.png", "frames": 2, "speed": 0.5},
    {"path": "ship3.png", "frames": 2, "speed": 0.8},
    {"path": "Cutter.png", "frames": 2, "speed": 0.3},
    {"path": "Tender.png", "frames": 2, "speed": 0.6},
    {"path": "flame.png", "frames": 5, "speed": 0.2},
    {"path": "monitor.png"},
    {"path": "smoke.png"},
    {"path": "cloud.png"},
    {"path": "wave_tile1.png"},
    {"path": "cannonball.png"},
    {"path": "soundtrack.ogg"},
    {"path": "cannon.ogg"},
    {"path": "scatter.ogg"},
    {"path": "smallHit.ogg"},
    {"path": "swosh.ogg"},
    {"path": "hit.ogg"}
  ],
  "fontFamily": "Visitor"
}